.gitignore
.travis.yml
CONTRIBUTING.md
LICENSE.md
MANIFEST.in
README.md
setup.cfg
setup.py
docs/tdu/cli.rst
src/tdu/ThrusterDesign.py
src/tdu/__init__.py
src/tdu/cli.py
src/tdu/config.ini
src/tdu.egg-info/PKG-INFO
src/tdu.egg-info/SOURCES.txt
src/tdu.egg-info/dependency_links.txt
src/tdu.egg-info/entry_points.txt
src/tdu.egg-info/top_level.txt