Metadata-Version: 1.1
Name: tdu
Version: 0.0.1
Summary: Thruster design utility.
Home-page: https://github.com/runphilrun/tdu
Author: Phil-Linden
Author-email: pjl7651@rit.edu
License: Apache-2.0
Download-URL: https://github.com/runphilrun/tdu/tarball/0.1
Platform: UNKNOWN
Classifier: Development Status :: 1 - Planning
Classifier: Intended Audience :: Science/Research
Classifier: Topic :: Scientific/Engineering
Classifier: Topic :: Utilities
Classifier: License :: OSI Approved :: Apache Software License
Classifier: Operating System :: OS Independent
Classifier: Programming Language :: Python :: 3 :: Only
